{
  "trails": [
    {
      "id": 1,
      "name": "Ascensión al Mulhacén",
      "location": "Sierra Nevada, Granada",
      "image": "https://images.ecestaticos.com/dAPVS4J5hNn23Swn5b7b9yT31dI=/0x0:2121x1414/1200x900/filters:fill(white):format(jpg)/f.elconfidencial.com%2Foriginal%2F8f5%2F3e3%2F961%2F8f53e3961ed4e3237d6582414757c66c.jpg",
      "imageHint": "cumbre Mulhacén",
      "difficulty": "Hard",
      "terrain": "Mountain",
      "length": 18.5,
      "duration": 8,
      "rating": 4.9,
      "description": "Una ruta exigente que te lleva a la cima más alta de la Península Ibérica. Vistas espectaculares de 360 grados de Sierra Nevada y, en días claros, del Mediterráneo y África. Requiere buena condición física.",
      "stravaEmbed": {
        "type": "route",
        "id": "3326141520730353078"
      }
    },
    {
      "id": 2,
      "name": "Ruta de los Cahorros",
      "location": "Monachil, Granada",
      "image": "https://www.actualidadiphone.com/wp-content/uploads/2016/09/maps-rutas-830x467.jpg",
      "imageHint": "puentes colgantes Cahorros",
      "difficulty": "Moderate",
      "terrain": "Forest",
      "length": 8,
      "duration": 4,
      "rating": 4.7,
      "description": "Una espectacular ruta que combina puentes colgantes, cascadas y desfiladeros estrechos. Ideal para una aventura de medio día. No apta para personas con vértigo.",
      "stravaEmbed": {
        "type": "route",
        "id": "27599026"
      }
    }
  ]
}
